dialetica/__init__.py
dialetica/client.py
dialetica/models.py
dialetica-1.0.23.dist-info/METADATA
dialetica-1.0.23.dist-info/WHEEL
dialetica-1.0.23.dist-info/top_level.txt
dialetica-1.0.23.dist-info/RECORD
