Metadata-Version: 2.4
Name: dialetica
Version: 1.0.23
Summary: Python SDK for Dialetica AI - Multi-agent conversational AI platform
Author-email: Dialetica AI <support@dialetica-ai.com>
License: MIT
Project-URL: Homepage, https://github.com/your-org/dialetica-ai
Project-URL: Documentation, https://docs.dialetica-ai.com
Project-URL: Repository, https://github.com/your-org/dialetica-ai
Project-URL: Issues, https://github.com/your-org/dialetica-ai/issues
Keywords: ai,llm,multi-agent,conversational-ai,dialetica
Classifier: Development Status :: 4 - Beta
Classifier: Intended Audience :: Developers
Classifier: License :: OSI Approved :: MIT License
Classifier: Programming Language :: Python :: 3
Classifier: Programming Language :: Python :: 3.8
Classifier: Programming Language :: Python :: 3.9
Classifier: Programming Language :: Python :: 3.10
Classifier: Programming Language :: Python :: 3.11
Classifier: Programming Language :: Python :: 3.12
Classifier: Topic :: Software Development :: Libraries :: Python Modules
Classifier: Topic :: Scientific/Engineering :: Artificial Intelligence
Requires-Python: >=3.8
Requires-Dist: pydantic>=2.9.0
Requires-Dist: requests>=2.31.0
Requires-Dist: httpx>=0.24.0
Provides-Extra: dev
Requires-Dist: pytest>=7.0.0; extra == "dev"
Requires-Dist: black>=23.0.0; extra == "dev"
Requires-Dist: mypy>=1.0.0; extra == "dev"
